plone.jsonserializer-0.9.11-py3.10-nspkg.pth
plone/jsonserializer/__init__.py
plone/jsonserializer/configure.zcml
plone/jsonserializer/exceptions.py
plone/jsonserializer/interfaces.py
plone/jsonserializer/testing.py
plone/jsonserializer/deserializer/__init__.py
plone/jsonserializer/deserializer/configure.zcml
plone/jsonserializer/deserializer/converters.py
plone/jsonserializer/serializer/__init__.py
plone/jsonserializer/serializer/configure.zcml
plone/jsonserializer/serializer/converters.py
plone/jsonserializer/tests/__init__.py
plone/jsonserializer/types/__init__.py
plone/jsonserializer/types/adapters.py
plone/jsonserializer/types/configure.zcml
plone/jsonserializer/types/interfaces.py
plone/jsonserializer/types/utils.py
plone.jsonserializer-0.9.11.dist-info/METADATA
plone.jsonserializer-0.9.11.dist-info/WHEEL
plone.jsonserializer-0.9.11.dist-info/entry_points.txt
plone.jsonserializer-0.9.11.dist-info/namespace_packages.txt
plone.jsonserializer-0.9.11.dist-info/top_level.txt
plone.jsonserializer-0.9.11.dist-info/RECORD
