Metadata-Version: 2.1
Name: plone.jsonserializer
Version: 0.9.11
Summary: JSON serialization/deserialization adapters for Plone.
Home-page: https://github.com/pyrenees/plone.jsonserializer/
Author: Plone Foundation
Author-email: foundation@plone.org
License: gpl
Keywords: plone json serializer
Classifier: Development Status :: 5 - Production/Stable
Classifier: Environment :: Web Environment
Classifier: Framework :: Plone
Classifier: Framework :: Plone :: 5.0
Classifier: Framework :: Plone :: 5.1
Classifier: Framework :: Plone :: 5.2
Classifier: Framework :: Plone :: 6.0
Classifier: Framework :: Plone :: Addon
Classifier: License :: OSI Approved :: GNU General Public License v2 (GPLv2)
Classifier: Programming Language :: Python
Classifier: Programming Language :: Python :: 2.7
Classifier: Programming Language :: Python :: 3.6
Classifier: Programming Language :: Python :: 3.7
Classifier: Programming Language :: Python :: 3.8
Classifier: Programming Language :: Python :: 3.9
Classifier: Programming Language :: Python :: 3.10
Classifier: Programming Language :: Python :: 3.11
Classifier: Topic :: Software Development :: Libraries :: Python Modules
Requires-Dist: setuptools
Provides-Extra: test
Requires-Dist: plone.app.testing (>=4.2.2) ; extra == 'test'
